libvirt_vm_optimizer/__init__.py
libvirt_vm_optimizer/__main__.py
libvirt_vm_optimizer/operation/__init__.py
libvirt_vm_optimizer/operation/data.py
libvirt_vm_optimizer/operation/elements.py
libvirt_vm_optimizer/operation/optimize.py
libvirt_vm_optimizer/operation/util.py
libvirt_vm_optimizer/operation/capabilities/__init__.py
libvirt_vm_optimizer/operation/capabilities/capabilities.py
libvirt_vm_optimizer/operation/capabilities/domain.py
libvirt_vm_optimizer/operation/cpupinning/__init__.py
libvirt_vm_optimizer/operation/cpupinning/cell_pinning.py
libvirt_vm_optimizer/util/__init__.py
libvirt_vm_optimizer/util/arg_parser.py
libvirt_vm_optimizer/util/utils.py
libvirt_vm_optimizer-0.0.9.dist-info/LICENSE
libvirt_vm_optimizer-0.0.9.dist-info/METADATA
libvirt_vm_optimizer-0.0.9.dist-info/WHEEL
libvirt_vm_optimizer-0.0.9.dist-info/entry_points.txt
libvirt_vm_optimizer-0.0.9.dist-info/top_level.txt
libvirt_vm_optimizer-0.0.9.dist-info/RECORD
