Metadata-Version: 2.1
Name: libvirt-vm-optimizer
Version: 0.0.9
Summary: Optimization for libvirt VMs (QEMU/KVM)
Home-page: https://github.com/suomiy/libvirt-vm-optimizer
Author: suomiy
License: UNKNOWN
Platform: UNKNOWN
Classifier: Programming Language :: Python :: 3
Classifier: License :: OSI Approved :: MIT License
Classifier: Operating System :: OS Independent
Classifier: Development Status :: 3 - Alpha
Requires-Python: >=3
Requires-Dist: lxml
